historical_currencies/__init__.py
historical_currencies/admin.py
historical_currencies/apps.py
historical_currencies/choices.py
historical_currencies/exceptions.py
historical_currencies/exchange.py
historical_currencies/formatting.py
historical_currencies/models.py
historical_currencies/py.typed
historical_currencies/management/__init__.py
historical_currencies/management/commands/__init__.py
historical_currencies/management/commands/import_ecb_exchangerates.py
historical_currencies/management/commands/import_openexchangerates.py
historical_currencies/migrations/0001_initial.py
historical_currencies/migrations/__init__.py
historical_currencies/templates/historical_currencies/currency_choices_options.html
historical_currencies/templatetags/__init__.py
historical_currencies/templatetags/currency_choices.py
historical_currencies/templatetags/currency_format.py
historical_currencies/tests/__init__.py
historical_currencies/tests/test_checks.py
historical_currencies/tests/test_exchange.py
historical_currencies/tests/test_formatting.py
historical_currencies/tests/test_importers.py
historical_currencies/tests/test_models.py
historical_currencies/tests/test_templatetags.py
django_historical_currencies-0.0.3.dist-info/LICENSE
django_historical_currencies-0.0.3.dist-info/METADATA
django_historical_currencies-0.0.3.dist-info/WHEEL
django_historical_currencies-0.0.3.dist-info/top_level.txt
django_historical_currencies-0.0.3.dist-info/RECORD
