Metadata-Version: 2.1
Name: django-historical-currencies
Version: 0.0.3
Summary: Django currencies with historical exchange rates
Author-email: Stefano Rivera <stefano@rivera.za.net>
License: ISC
Project-URL: Repository, https://github.com/stefanor/django-historical-currencies/
Project-URL: Changelog, https://github.com/stefanor/django-historical-currencies/blob/master/CHANGELOG.md
Keywords: django,currencies,exchange,xe
Classifier: Framework :: Django
Classifier: Programming Language :: Python :: 3
Classifier: Typing :: Typed
Requires-Python: >=3.7
License-File: LICENSE
Requires-Dist: django
Requires-Dist: iso4217
